README.txt
setup.py
freespira/__init__.py
freespira/in_house_elog_scraper.py
freespira/main.py
freespira.test.new.egg-info/PKG-INFO
freespira.test.new.egg-info/SOURCES.txt
freespira.test.new.egg-info/dependency_links.txt
freespira.test.new.egg-info/not-zip-safe
freespira.test.new.egg-info/requires.txt
freespira.test.new.egg-info/top_level.txt