Metadata-Version: 1.0
Name: freespira.test.new
Version: 0.1.6
Summary: test library for freespira code
Home-page: UNKNOWN
Author: Sean Reynolds and Paul Graham
Author-email: sean@freespira.com, paul@freespira.com
License: UNKNOWN
Platform: UNKNOWN
